Num_CFS_Cluster-0.2.dist-info/METADATA
Num_CFS_Cluster-0.2.dist-info/RECORD
Num_CFS_Cluster-0.2.dist-info/WHEEL
Num_CFS_Cluster-0.2.dist-info/top_level.txt
Numerical_CFS/API_Main.py
Numerical_CFS/Action.py
Numerical_CFS/ActionGraph.py
Numerical_CFS/Diag_Schar.py
Numerical_CFS/FlowChartMaker.py
Numerical_CFS/LibForSimulAnnealing.py
Numerical_CFS/Lib_Action_Minimum.py
Numerical_CFS/PyxPlot3d.py
Numerical_CFS/PyxSchar.py
Numerical_CFS/SymEngineFast.py
Numerical_CFS/Test.py
Numerical_CFS/__init__.py
Numerical_CFS/configfunktion.py
Numerical_CFS/config/Settings.cfg
Numerical_CFS/data/funcprint.c
